uvscem/__init__.py
uvscem/api_client.py
uvscem/code_manager.py
uvscem/extension_manager.py
uvscem-0.1.3.dist-info/LICENSE
uvscem-0.1.3.dist-info/METADATA
uvscem-0.1.3.dist-info/WHEEL
uvscem-0.1.3.dist-info/entry_points.txt
uvscem-0.1.3.dist-info/RECORD
